{
  "fishes": [
    {
      "name": "マグロ",
      "features": "赤身で味が濃厚、刺身や寿司の定番",
      "nutrition": "良質なタンパク質、ビタミンB群、DHA",
      "origin": "太平洋、大西洋、インド洋"
    },
    {
      "name": "サーモン",
      "features": "脂がのっていて柔らかい身質、生食や焼き魚に適する",
      "nutrition": "オメガ3脂肪酸、ビタミンD、タンパク質",
      "origin": "北太平洋、北大西洋"
    },
    {
      "name": "タイ",
      "features": "白身で淡泊な味わい、祝い事に用いられることが多い",
      "nutrition": "低カロリー、良質なタンパク質、ビタミンB群",
      "origin": "日本近海"
    },
    {
      "name": "サバ",
      "features": "青魚特有の脂の乗った味わい、塩焼きや味噌煮が人気",
      "nutrition": "EPA、DHA、ビタミンD",
      "origin": "日本近海、北太平洋"
    },
    {
      "name": "アジ",
      "features": "さっぱりとした味わいの青魚、塩焼きや刺身で食べられる",
      "nutrition": "ビタミンB1、EPA、タウリン",
      "origin": "日本近海"
    },
    {
      "name": "イワシ",
      "features": "小骨が多いが栄養価が高い、缶詰でも人気",
      "nutrition": "カルシウム、DHA、ビタミンD",
      "origin": "世界中の温帯から熱帯の海"
    },
    {
      "name": "カツオ",
      "features": "濃厚な味わいの赤身魚、たたきや刺身が有名",
      "nutrition": "ビタミンB群、タウリン、DHA",
      "origin": "太平洋、インド洋"
    },
    {
      "name": "ブリ",
      "features": "出世魚として知られる、冬が旬",
      "nutrition": "DHA、EPA、ビタミンB群",
      "origin": "日本近海"
    },
    {
      "name": "タラ",
      "features": "白身で淡泊、鍋料理や煮付けに適する",
      "nutrition": "タンパク質、ビタミンB群、ミネラル",
      "origin": "北太平洋、北大西洋"
    },
    {
      "name": "サンマ",
      "features": "秋の味覚として有名、塩焼きが定番",
      "nutrition": "EPA、DHA、ビタミンA",
      "origin": "北太平洋"
    },
    {
      "name": "ヒラメ",
      "features": "高級白身魚、刺身や煮付けで食べられる",
      "nutrition": "低カロリー、良質なタンパク質、ビタミンB群",
      "origin": "日本近海"
    },
    {
      "name": "アナゴ",
      "features": "ウナギに似た味わい、天ぷらや寿司ネタとして人気",
      "nutrition": "ビタミンA、E、カルシウム",
      "origin": "日本近海、東シナ海"
    },
    {
      "name": "カレイ",
      "features": "平たい形状の白身魚、煮付けや唐揚げに適する",
      "nutrition": "低カロリー、タンパク質、ビタミンA",
      "origin": "日本近海、北太平洋"
    },
    {
      "name": "ホッケ",
      "features": "脂がのった白身魚、開きや塩焼きが一般的",
      "nutrition": "EPA、DHA、ビタミンD",
      "origin": "北太平洋"
    },
    {
      "name": "メバチマグロ",
      "features": "脂がのった赤身で、刺身や寿司に最適",
      "nutrition": "タンパク質、ビタミンB群、セレン",
      "origin": "熱帯・亜熱帯の海域"
    }
  ],
  "fish_seasons": [
    {
      "fish": "マグロ",
      "start_date": "2024-06-01",
      "end_date": "2024-08-31"
    },
    {
      "fish": "サーモン",
      "start_date": "2024-09-01",
      "end_date": "2024-11-30"
    },
    {
      "fish": "タイ",
      "start_date": "2024-04-01",
      "end_date": "2024-06-30"
    },
    {
      "fish": "サバ",
      "start_date": "2024-09-01",
      "end_date": "2024-11-30"
    },
    {
      "fish": "アジ",
      "start_date": "2024-05-01",
      "end_date": "2024-07-31"
    },
    {
      "fish": "イワシ",
      "start_date": "2024-06-01",
      "end_date": "2024-08-31"
    },
    {
      "fish": "カツオ",
      "start_date": "2024-04-01",
      "end_date": "2024-06-30"
    },
    {
      "fish": "ブリ",
      "start_date": "2024-12-01",
      "end_date": "2025-02-28"
    },
    {
      "fish": "タラ",
      "start_date": "2024-11-01",
      "end_date": "2025-01-31"
    },
    {
      "fish": "サンマ",
      "start_date": "2024-09-01",
      "end_date": "2024-11-30"
    },
    {
      "fish": "ヒラメ",
      "start_date": "2024-11-01",
      "end_date": "2025-01-31"
    },
    {
      "fish": "アナゴ",
      "start_date": "2024-06-01",
      "end_date": "2024-08-31"
    },
    {
      "fish": "カレイ",
      "start_date": "2024-02-01",
      "end_date": "2024-04-30"
    },
    {
      "fish": "ホッケ",
      "start_date": "2024-10-01",
      "end_date": "2024-12-31"
    },
    {
      "fish": "メバチマグロ",
      "start_date": "2024-07-01",
      "end_date": "2024-09-30"
    }
  ]
}
